{
  "schemaVersion": 2,
  "frequencySourceDecision": {
    "status": "selected-for-phase-0",
    "canonicalFrequencySource": "hermitdave/FrequencyWords Spanish OpenSubtitles frequency list",
    "sourceUrl": "https://github.com/hermitdave/FrequencyWords",
    "license": "CC-BY-SA-4.0 for generated content outputs",
    "upstreamCorpus": "OpenSubtitles",
    "decision": "Use this source as the canonical ordering spine for Spanish frequency ranks. Store rank provenance separately from authored curriculum text, expose attribution in the in-app credits screen, and treat any redistributed rank data as CC-BY-SA-4.0.",
    "rationale": [
      "The repo publishes generated outputs and identifies CC-BY-SA-4.0 for content.",
      "The list is broad enough for the A1/A2/B1 frequency spine and already matches SPEC O1 candidates.",
      "The ShareAlike obligation is manageable if frequency-derived metadata is explicitly attributed and segregated."
    ],
    "licenseNotes": [
      {
        "source": "Tatoeba textual sentences",
        "url": "https://tatoeba.org/en/downloads",
        "license": "CC-BY-2.0-FR or CC0 depending on download/subset",
        "use": "Spanish-English sentence pairs and accepted-answer source pairs"
      },
      {
        "source": "Wiktionary",
        "url": "https://en.wiktionary.org/wiki/Wiktionary:Copyrights",
        "license": "CC-BY-SA / GFDL for entry text",
        "use": "Glosses, part-of-speech data, and conjugation source checks"
      }
    ]
  },
  "targetListSource": {
    "status": "phase-0-audit-list",
    "sourceBasis": [
      "SPEC.md \u00a74.1 vocabulary spine and \u00a75.6 CEFR sequencing",
      "SPANISH_BREADTH_PLAN.md Phase 0/Phase 1 A1-A2 priorities",
      "hermitdave/FrequencyWords selected ordering spine"
    ],
    "reviewPolicy": "This list is a local source-checked audit target, not shipped learning content. A target lemma only becomes shipped content after the normal lexeme/sentence/accepted-answer provenance and REVIEWED gate pass."
  },
  "summary": {
    "rawLexemes": 276,
    "learnerReadyLexemes": 276,
    "reviewedSentences": 612,
    "reviewedAcceptedAnswers": 615,
    "exerciseCount": 552,
    "missingA1A2GapCount": 0
  },
  "counts": {
    "lexemesByPos": {
      "adjective": 42,
      "adjective/adverb": 4,
      "adverb": 10,
      "adverb/noun": 1,
      "noun": 56,
      "verb": 163
    },
    "lexemesByCefrBand": {
      "A1": 23,
      "A2": 103,
      "B1": 150
    },
    "lexemesByFrequencyBucket": {
      "0001-0500": 62,
      "0501-1000": 59,
      "1001-2000": 128,
      "2001+": 27
    },
    "contentRowsBySource": {
      "ai_draft": 1024,
      "authored": 2,
      "tatoeba": 201,
      "wiktionary": 276
    },
    "contentRowsByLicense": {
      "CC-BY-2.0-FR": 201,
      "CC-BY-SA-3.0": 276,
      "proprietary": 1026
    },
    "contentRowsByVettingStatus": {
      "REVIEWED": 1503
    },
    "exerciseTargetsByType": {
      "LEXEME": 552
    },
    "exerciseTypes": {
      "TYPED_TRANSLATION": 276,
      "WORD_BANK": 276
    }
  },
  "topMissingA1A2Gaps": []
}
